postqf/__init__.py
postqf/__main__.py
postqf/config.py
postqf/core.py
postqf/filter.py
postqf/logstuff.py
tests/__init__.py
tests/test_config.py
tests/test_core.py
tests/test_filter.py
postqf-0.5.dist-info/LICENSE
postqf-0.5.dist-info/METADATA
postqf-0.5.dist-info/WHEEL
postqf-0.5.dist-info/entry_points.txt
postqf-0.5.dist-info/top_level.txt
postqf-0.5.dist-info/RECORD
