Metadata-Version: 2.1
Name: postqf
Version: 0.5
Summary: User-friendly Postfix queue data filter
Home-page: https://github.com/rseichter/postqf
Author: Ralph Seichter
Author-email: postqf@seichter.de
License: UNKNOWN
Platform: UNKNOWN
Classifier: Development Status :: 5 - Production/Stable
Classifier: License :: OSI Approved :: GNU General Public License v3 or later (GPLv3+)
Classifier: Operating System :: OS Independent
Classifier: Programming Language :: Python :: 3.7
Classifier: Topic :: System :: Systems Administration
Classifier: Topic :: Utilities
Requires-Python: >=3.7
License-File: LICENSE
